{"name":"NodeJS","slug":"NodeJS","count":1,"postlist":[{"title":"NodeJS Stream","uid":"495c7f3561d14b86e5bb70506dad2bf9","slug":"nodejs-stream","date":"2022-03-19T10:44:57.000Z","updated":"2022-03-20T12:04:59.172Z","comments":true,"path":"api/articles/nodejs-stream.json","keywords":null,"cover":[],"text":" Streams are Node’s best and most misunderstood idea. – Dominic Tarr Stream 是什么？ Streams are collections of data – just like arrays or strin...","link":"","photos":[],"count_time":{"symbolsCount":"11k","symbolsTime":"10 mins."},"categories":[],"tags":[{"name":"NodeJS","slug":"NodeJS","count":1,"path":"api/tags/NodeJS.json"}],"author":{"name":"Matrix","slug":"blog-author","avatar":"https://p1-jj.byteimg.com/tos-cn-i-t2oaga2asx/gold-user-assets/2019/8/2/16c515569d19fc87~tplv-t2oaga2asx-no-mark:500:500:500:500.awebp","link":"/","description":"","socials":{"github":"","twitter":"","stackoverflow":"","wechat":"","qq":"","weibo":"","zhihu":"","csdn":"","juejin":"","customs":{}}},"feature":true}]}